enki/__init__.py
enki/dataframer.py
enki/exceptions.py
enki/task_loaders.py
enki/task_run_loaders.py
enki-1.1.2.dist-info/DESCRIPTION.rst
enki-1.1.2.dist-info/METADATA
enki-1.1.2.dist-info/RECORD
enki-1.1.2.dist-info/WHEEL
enki-1.1.2.dist-info/metadata.json
enki-1.1.2.dist-info/top_level.txt
