Metadata-Version: 2.0
Name: enki
Version: 1.1.2
Summary: A Python library to analyze PYBOSSA project's results
Home-page: https://github.com/Scifabric/enki
Author: Scifabric LTD
Author-email: info@scifabric.com
License: AGPLv3
Download-URL: https://github.com/Scifabric/enki/zipball/master
Platform: UNKNOWN
Classifier: Development Status :: 5 - Production/Stable
Classifier: Environment :: Console
Classifier: Intended Audience :: Developers
Classifier: License :: OSI Approved :: GNU Affero General Public License v3 or later (AGPLv3+)
Classifier: Operating System :: OS Independent
Classifier: Programming Language :: Python
Classifier: Topic :: Software Development :: Libraries :: Python Modules
Classifier: Topic :: Scientific/Engineering
Requires-Dist: pandas
Requires-Dist: pybossa-client (>=2.0.1,<2.0.2)
